{
  "client": [
    {
      "services": {
        "appinvite_service": {
          "status": 1
        }, 
        "analytics_service": {
          "status": 0
        }
      }, 
      "oauth_client": [
        {
          "client_id": "966641733414-lneum992t5l04bbnu81ur7qgou2m40tm.apps.googleusercontent.com"
        }
      ], 
      "api_key": [
        {
          "current_key": "AIzaSyC5lqgRLMK-UfxYXw-eoBWdcTLljx5xj1o"
        }
      ], 
      "client_info": {
        "mobilesdk_app_id": "1:966641733414:ios:713e941afe3f4208", 
        "android_client_info": {
          "package_name": "com.diyar.denealfit"
        }
      }
    }
  ], 
  "configuration_version": "1", 
  "project_info": {
    "storage_bucket": "diyar-unity.appspot.com", 
    "project_id": "diyar-unity", 
    "firebase_url": "https://diyar-unity.firebaseio.com", 
    "project_number": "966641733414"
  }
}